epure/__init__.py
epure/dbs.py
epure/epure.py
epure/errors.py
epure/files.py
epure/generics.py
epure/helpers/__init__.py
epure/helpers/dict_helper.py
epure/helpers/string_helper.py
epure/helpers/type_helper.py
epure/named.py
epure/parser/__init__.py
epure/parser/bin_operation.py
epure/parser/binary.py
epure/parser/inspect_parser/__init__.py
epure/parser/inspect_parser/column_proxy.py
epure/parser/inspect_parser/domain.py
epure/parser/inspect_parser/inspect_parser.py
epure/parser/inspect_parser/model.py
epure/parser/inspect_parser/term.py
epure/parser/leaf.py
epure/parser/proxy_base_cls.py
epure/parser/term.py
epure/parser/term_debugger.py
epure/parser/term_parser.py
epure/resource/__init__.py
epure/resource/data_promise.py
epure/resource/db/__init__.py
epure/resource/db/constraint.py
epure/resource/db/db.py
epure/resource/db/db_entity.py
epure/resource/db/db_entity_resource.py
epure/resource/db/pseudo_table.py
epure/resource/db/query_old.py
epure/resource/db/select_query.py
epure/resource/db/table.py
epure/resource/db/table_column.py
epure/resource/db/table_header.py
epure/resource/db/table_storage.py
epure/resource/db/term.py
epure/resource/edata/__init__.py
epure/resource/edata/ecollection_metacls.py
epure/resource/edata/edata.py
epure/resource/edata/elist.py
epure/resource/edata/proto.py
epure/resource/file/__init__.py
epure/resource/file/file_storage.py
epure/resource/file/ini_file.py
epure/resource/file/ini_section.py
epure/resource/file/json_file.py
epure/resource/gres/__init__.py
epure/resource/gres/gres_db.py
epure/resource/gres/gres_entity.py
epure/resource/gres/gres_header.py
epure/resource/gres/gres_table.py
epure/resource/gres/jsonb_table.py
epure/resource/join_resource/join_resource.py
epure/resource/lite_db/lite_db.py
epure/resource/lite_db/lite_table.py
epure/resource/resource.py
epure/resource/savable.py
epure-0.3.13.dist-info/METADATA
epure-0.3.13.dist-info/WHEEL
epure-0.3.13.dist-info/RECORD
