Metadata-Version: 2.1
Name: epure
Version: 0.3.13
Summary: purest architecture
License: MIT
Author: Nikita Umarov
Author-email: nagvalhm@yandex.ru
Requires-Python: >=3.10,<4.0
Classifier: License :: OSI Approved :: MIT License
Classifier: Programming Language :: Python :: 3
Classifier: Programming Language :: Python :: 3.10
Classifier: Programming Language :: Python :: 3.11
Requires-Dist: inflection (>=0.5.1,<0.6.0)
Requires-Dist: jsonpickle (>=2.2.0,<3.0.0)
Requires-Dist: psycopg2 (==2.9.3)
Project-URL: Documentation, https://github.com/nagvalhm/epure/blob/main/README.md
Project-URL: Homepage, https://github.com/nagvalhm/epure
Project-URL: Source, https://github.com/nagvalhm/epure
